ion_client/__init__.py
ion_client/client.py
ion_client/logger.py
ion_client/sso.py
ion_client-1.1.0.dist-info/LICENSE
ion_client-1.1.0.dist-info/METADATA
ion_client-1.1.0.dist-info/WHEEL
ion_client-1.1.0.dist-info/RECORD
