Metadata-Version: 2.1
Name: ion-client
Version: 1.1.0
Summary: Aruba Instant On client
License: MIT
Author: Maxime Mouchet
Author-email: max@maxmouchet.com
Requires-Python: >=3.10,<4.0
Classifier: License :: OSI Approved :: MIT License
Classifier: Programming Language :: Python :: 3
Classifier: Programming Language :: Python :: 3.10
Classifier: Programming Language :: Python :: 3.11
Classifier: Programming Language :: Python :: 3.12
Classifier: Programming Language :: Python :: 3.13
Requires-Dist: httpx (>=0.27.0,<0.28.0)
